Workbook

Sheet CMDB_servers_operational
A1: Name | B1: Application Relationship | C1: Support Group | D1: Operational status | E1: Most recent discovery | F1: Duplicate Of | G1: Fully qualified domain name | H1: Operating System | I1: Environment | J1: Sub-Environment | K1: Application Relationship | L1: IP Address | M1: DNS Domain | N1: Domain | O1: OS Version
A2: eac2sqbapl10v | B2: SonarQube-CVS | C2: =VLOOKUP(B2,CMDB_Apps!B:J,9,FALSE) -> DevOps Engineering | D2: Operational | E2: 46070.147 | G2: eac2sqbapl10v.corp.cvscaremark.com | H2: Linux Red Hat | I2: PROD | J2: PROD | K2: SonarQube-CVS | L2: 10.223.153.21 | M2: corp.cvscaremark.com | N2: global | O2: 7.9
A3: rac2ctrapl10v | B3: RXDW IDW | C3: =VLOOKUP(B3,CMDB_Apps!B:J,9,FALSE) -> PS RX DATA WAREHOUSE IDW RDL | D3: Operational | E3: 46070.147 | G3: rac2ctrapl10v.corp.cvscaremark.com | H3: Linux Red Hat | I3: PROD | J3: PROD | K3: RXDW IDW | L3: 10.223.153.13 | M3: corp.cvscaremark.com | N3: global | O3: 7.9
A4: rac2ctradl10v | B4: RXDW IDW | C4: =VLOOKUP(B4,CMDB_Apps!B:J,9,FALSE) -> PS RX DATA WAREHOUSE IDW RDL | D4: Operational | E4: 46070.146 | G4: rac2ctradl10v.corp.cvscaremark.com | H4: Linux Red Hat | I4: DEV | J4: Development | K4: RXDW IDW | L4: 10.223.185.12 | M4: corp.cvscaremark.com | N4: global | O4: 7.9
A5: rac2ctraql10v | B5: RXDW IDW | C5: =VLOOKUP(B5,CMDB_Apps!B:J,9,FALSE) -> PS RX DATA WAREHOUSE IDW RDL | D5: Operational | E5: 46070.146 | G5: rac2ctraql10v.corp.cvscaremark.com | H5: Linux Red Hat | I5: TEST | J5: UAT | K5: RXDW IDW | L5: 10.223.185.14 | M5: corp.cvscaremark.com | N5: global | O5: 7.9
A6: pac4cdiwpl10v | B6: Document Indexing Application | C6: =VLOOKUP(B6,CMDB_Apps!B:J,9,FALSE) -> CORAM-DIA | D6: Operational | E6: 46070.146 | G6: pac4cdiwpl10v.corp.cvscaremark.com | H6: Linux Red Hat | I6: PROD | J6: PROD | K6: Document Indexing Application | L6: 10.223.66.166 | M6: corp.cvscaremark.com | N6: global | O6: 8.10
A7: pac4cdiwpl11v | B7: Document Indexing Application | C7: =VLOOKUP(B7,CMDB_Apps!B:J,9,FALSE) -> CORAM-DIA | D7: Operational | E7: 46070.146 | G7: pac4cdiwpl11v.corp.cvscaremark.com | H7: Linux Red Hat | I7: PROD | J7: PROD | K7: Document Indexing Application | L7: 10.223.66.167 | M7: corp.cvscaremark.com | N7: global | O7: 8.10
A8: rac4sphfpl10v | B8: SPLUNK - NON PCI | C8: =VLOOKUP(B8,CMDB_Apps!B:J,9,FALSE) -> TSS-Ops-Support-Observability | D8: Operational | E8: 46070.142 | G8: rac4sphfpl10v.corp.cvscaremark.com | H8: Linux Red Hat | I8: PROD | J8: PROD | K8: SPLUNK - NON PCI | L8: 10.223.192.5 | M8: corp.cvscaremark.com | N8: global | O8: 8.10
A9: pac4vbrxdpl10v | B9: VBRX | C9: =VLOOKUP(B9,CMDB_Apps!B:J,9,FALSE) -> 0 | D9: Operational | E9: 46070.13 | G9: pac4vbrxdpl10v.corp.cvscaremark.com | H9: Linux Red Hat | I9: PROD | J9: PROD | K9: VBRX | L9: 10.175.175.196 | M9: corp.cvscaremark.com | N9: global | O9: 8.10
A10: pac4vbrxddl10v | B10: VBRX | C10: =VLOOKUP(B10,CMDB_Apps!B:J,9,FALSE) -> 0 | D10: Operational | E10: 46070.128 | G10: pac4vbrxddl10v.corp.cvscaremark.com | H10: Linux Red Hat | I10: DEV | J10: DEV1 | K10: VBRX | L10: 10.175.128.4 | M10: corp.cvscaremark.com | N10: global | O10: 8.10
A11: pac4vbrxdnl10v | B11: VBRX | C11: =VLOOKUP(B11,CMDB_Apps!B:J,9,FALSE) -> 0 | D11: Operational | E11: 46070.128 | G11: pac4vbrxdnl10v.corp.cvscaremark.com | H11: Linux Red Hat | I11: TEST | J11: UAT | K11: VBRX | L11: 10.175.128.5 | M11: corp.cvscaremark.com | N11: global | O11: 8.10
A12: rac2cdpapl1v | B12: Customer Data Platform (CDP) | C12: =VLOOKUP(B12,CMDB_Apps!B:J,9,FALSE) -> 0 | D12: Operational | E12: 46070.127 | G12: rac2cdpapl1v.corp.cvscaremark.com | H12: Linux Red Hat | I12: PROD | J12: PROD | K12: Customer Data Platform (CDP) | L12: 10.175.2.7 | M12: corp.cvscaremark.com | N12: global | O12: 7.9
A13: paz1micrpl18v | B13: MICROSTRATEGY - PBM | C13: =VLOOKUP(B13,CMDB_Apps!B:J,9,FALSE) -> 0 | D13: Operational | E13: 46070.067 | G13: paz1micrpl18v.corp.cvscaremark.com | H13: Linux Red Hat | I13: PROD | J13: PROD | K13: MICROSTRATEGY - PBM | L13: 10.217.188.122 | M13: corp.cvscaremark.com | N13: global | O13: 8.10
... A134: raz1rxfdpa50 | B134: ACQ2.0, RxConnect | C134: =VLOOKUP(B134,CMDB_Apps!B:J,9,FALSE) -> #N/A | D134: Operational | E134: 46070.044 | G134: raz1rxfdpa50.cvs.com | H134: AIX | I134: PROD | J134: PROD | K134: ACQ2.0, RxConnect | L134: 10.217.18.124 | M134: cvs.com | N134: global | O134: 7.2.0.0
A135: prdpps1a | B135: DISPENSING - PPS, DISPENSING - TRISTAR | C135: =VLOOKUP(B135,CMDB_Apps!B:J,9,FALSE) -> #N/A | D135: Operational | E135: 46069.957 | G135: prdpps1a.caremarkrx.net | H135: AIX | I135: PROD | J135: PROD | K135: DISPENSING - PPS, DISPENSING - TRISTAR | L135: 10.89.34.28 | N135: global | O135: 7.2.0.0
A136: prdpps1b | B136: DISPENSING - PPS | C136: =VLOOKUP(B136,CMDB_Apps!B:J,9,FALSE) -> PCW_IT_MailBackendDispensing_L2Support | D136: Operational | E136: 46069.956 | G136: prdpps1b.caremarkrx.net | H136: AIX | I136: PROD | J136: PROD | K136: DISPENSING - PPS | L136: 10.89.34.27 | N136: global | O136: 7.2.0.0
A137: prdtmq1a | B137: MAIL ORDER LETTERS AND FAXES, DISPENSING - TRISTAR, WEBSPHERE - MQ | C137: =VLOOKUP(B137,CMDB_Apps!B:J,9,FALSE) -> #N/A | D137: Operational | E137: 46069.956 | G137: prdtmq1a.caremarkrx.net | H137: AIX | I137: PROD | J137: PROD | K137: MAIL ORDER LETTERS AND FAXES, DISPENSING - TRISTAR, WEBSPHERE - MQ | L137: 10.89.34.22 | N137: global | O137: 7.2.0.0
A138: prdtdb1a | B138: DISPENSING - TRISTAR | C138: =VLOOKUP(B138,CMDB_Apps!B:J,9,FALSE) -> PCW_IT_MailBackendDispensing_L2Support | D138: Operational | E138: 46069.956 | G138: prdtdb1a.caremarkrx.net | H138: AIX | I138: PROD | J138: PROD | K138: DISPENSING - TRISTAR | L138: 10.89.34.24 | N138: global | O138: 7.2.0.0
A139: prdtmq1b | B139: WEBSPHERE - MQ, DISPENSING - TRISTAR | C139: =VLOOKUP(B139,CMDB_Apps!B:J,9,FALSE) -> #N/A | D139: Operational | E139: 46069.956 | G139: prdtmq1b.caremarkrx.net | H139: AIX | I139: PROD | J139: PROD | K139: WEBSPHERE - MQ, DISPENSING - TRISTAR | L139: 10.89.34.21 | N139: global | O139: 7.2.0.0
A140: wbpnim1 | B140: INFRASTRUCTURE UNIX TECH SERVICE, AIX - Solaris Nim-Jump Servers | C140: =VLOOKUP(B140,CMDB_Apps!B:J,9,FALSE) -> #N/A | D140: Operational | E140: 46069.956 | G140: wbpnim1.caremarkrx.net | H140: AIX | I140: TEST | J140: SANDBOX-TEST | K140: INFRASTRUCTURE UNIX TECH SERVICE, AIX - Solaris Nim-Jump Servers | L140: 10.89.34.18 | M140: none | N140: global | O140: 7.3.0.0
A141: pca1bcdbpl2v | B141: DISPENSING - SPECIALTY - PPS | C141: =VLOOKUP(B141,CMDB_Apps!B:J,9,FALSE) -> PCW_IT_SpecialtyBackendDispensing_L2Support | D141: Operational | E141: 46069.944 | G141: pca1bcdbpl2v.corp.cvscaremark.com | H141: Linux Red Hat | I141: PROD | J141: PROD | K141: DISPENSING - SPECIALTY - PPS | L141: 10.90.32.70 | M141: corp.cvscaremark.com | N141: global | O141: 7.9
A142: prdtrs2a | B142: DISPENSING - TRISTAR, MAIL ORDER LETTERS AND FAXES | C142: =VLOOKUP(B142,CMDB_Apps!B:J,9,FALSE) -> #N/A | D142: Operational | E142: 46069.931 | G142: prdtrs2a.caremarkrx.net | H142: AIX | I142: PROD | J142: PROD | K142: DISPENSING - TRISTAR, MAIL ORDER LETTERS AND FAXES | L142: 10.91.34.36 | M142: caremarkrx.net | N142: global | O142: 7.2.0.0
A143: prdpps2a | B143: DISPENSING - PPS, DISPENSING - TRISTAR | C143: =VLOOKUP(B143,CMDB_Apps!B:J,9,FALSE) -> #N/A | D143: Operational | E143: 46069.929 | G143: prdpps2a.caremarkrx.net | H143: AIX | I143: PROD | J143: PROD | K143: DISPENSING - PPS, DISPENSING - TRISTAR | L143: 10.91.34.18 | N143: global | O143: 7.2.0.0
A144: prdtdb2a | B144: DISPENSING - TRISTAR | C144: =VLOOKUP(B144,CMDB_Apps!B:J,9,FALSE) -> PCW_IT_MailBackendDispensing_L2Support | D144: Operational | E144: 46069.928 | G144: prdtdb2a.caremarkrx.net | H144: AIX | I144: PROD | J144: PROD | K144: DISPENSING - TRISTAR | L144: 10.91.34.21 | N144: global | O144: 7.2.0.0
A145: prdtmq2a | B145: MAIL ORDER LETTERS AND FAXES, DISPENSING - TRISTAR, WEBSPHERE - MQ | C145: =VLOOKUP(B145,CMDB_Apps!B:J,9,FALSE) -> #N/A | D145: Operational | E145: 46069.928 | G145: prdtmq2a.caremarkrx.net | H145: AIX | I145: PROD | J145: PROD | K145: MAIL ORDER LETTERS AND FAXES, DISPENSING - TRISTAR, WEBSPHERE - MQ | L145: 10.91.34.24 | N145: global | O145: 7.2.0.0
A146: prdtmq2b | B146: WEBSPHERE - MQ, DISPENSING - TRISTAR | C146: =VLOOKUP(B146,CMDB_Apps!B:J,9,FALSE) -> #N/A | D146: Operational | E146: 46069.928 | G146: prdtmq2b.caremarkrx.net | H146: AIX | I146: PROD | J146: PROD | K146: WEBSPHERE - MQ, DISPENSING - TRISTAR | L146: 10.91.34.25 | N146: global | O146: 7.2.0.0
A147: prdtdb2b | B147: DISPENSING - TRISTAR | C147: =VLOOKUP(B147,CMDB_Apps!B:J,9,FALSE) -> PCW_IT_MailBackendDispensing_L2Support | D147: Operational | E147: 46069.928 | G147: prdtdb2b.caremarkrx.net | H147: AIX | I147: PROD | J147: PROD | K147: DISPENSING - TRISTAR | L147: 10.91.34.22 | N147: global | O147: 7.2.0.0
A148: prdtrs2b | B148: DISPENSING - TRISTAR | C148: =VLOOKUP(B148,CMDB_Apps!B:J,9,FALSE) -> PCW_IT_MailBackendDispensing_L2Support | D148: Operational | E148: 46069.928 | G148: prdtrs2b.caremarkrx.net | H148: AIX | I148: PROD | J148: PROD | K148: DISPENSING - TRISTAR | L148: 10.91.34.28 | N148: global | O148: 7.2.0.0
A149: prdpps2b | B149: DISPENSING - PPS, DISPENSING - TRISTAR | C149: =VLOOKUP(B149,CMDB_Apps!B:J,9,FALSE) -> #N/A | D149: Operational | E149: 46069.928 | G149: prdpps2b.caremarkrx.net | H149: AIX | I149: PROD | J149: PROD | K149: DISPENSING - PPS, DISPENSING - TRISTAR | L149: 10.91.34.17 | N149: global | O149: 7.2.0.0
A150: chinim2 | B150: AIX - Solaris Nim-Jump Servers | C150: =VLOOKUP(B150,CMDB_Apps!B:J,9,FALSE) -> 0 | D150: Operational | E150: 46069.928 | G150: chinim2.caremarkrx.net | H150: AIX | I150: TEST | J150: SANDBOX-TEST | K150: AIX - Solaris Nim-Jump Servers | L150: 10.91.34.11 | M150: none | N150: global | O150: 7.3.0.0
A151: prdtbu2b | B151: EMC DATA PROTECTION ADVISOR, TIVOLI STORAGE MANAGER (TSM) | C151: =VLOOKUP(B151,CMDB_Apps!B:J,9,FALSE) -> #N/A | D151: Operational | E151: 46069.928 | G151: prdtbu2b.caremarkrx.net | H151: AIX | I151: PROD | J151: PROD | K151: EMC DATA PROTECTION ADVISOR, TIVOLI STORAGE MANAGER (TSM) | L151: 10.91.34.20 | N151: global | O151: 7.2.0.0
A152: paz1sppganl3v | B152: SpRx 2.0 | C152: =VLOOKUP(B152,CMDB_Apps!B:J,9,FALSE) -> SPRX 2.0 TIER 3 | D152: Operational | E152: 46069.925 | G152: paz1sppganl3v.corp.cvscaremark.com | H152: Linux Red Hat | I152: TEST | J152: PT | K152: SpRx 2.0 | L152: 10.9.80.102 | M152: corp.cvscaremark.com | N152: global | O152: 8.10
A153: paz1sppanl23v | B153: SpRx 2.0 | C153: =VLOOKUP(B153,CMDB_Apps!B:J,9,FALSE) -> SPRX 2.0 TIER 3 | D153: Operational | E153: 46069.925 | G153: paz1sppanl23v.corp.cvscaremark.com | H153: Linux Red Hat | I153: TEST | J153: PT | K153: SpRx 2.0 | L153: 10.9.80.106 | M153: corp.cvscaremark.com | N153: global | O153: 8.10
A154: paz1sppcnl11v | B154: SpRx 2.0 | C154: =VLOOKUP(B154,CMDB_Apps!B:J,9,FALSE) -> SPRX 2.0 TIER 3 | D154: Operational | E154: 46069.925 | G154: paz1sppcnl11v.corp.cvscaremark.com | H154: Linux Red Hat | I154: TEST | J154: PT | K154: SpRx 2.0 | L154: 10.9.62.221 | M154: corp.cvscaremark.com | N154: global | O154: 8.10
A155: paz1sppgnl11v | B155: SpRx 2.0 | C155: =VLOOKUP(B155,CMDB_Apps!B:J,9,FALSE) -> SPRX 2.0 TIER 3 | D155: Operational | E155: 46069.925 | G155: paz1sppgnl11v.corp.cvscaremark.com | H155: Linux Red Hat | I155: TEST | J155: PT | K155: SpRx 2.0 | L155: 10.9.62.216 | M155: corp.cvscaremark.com | N155: global | O155: 8.10
A156: raz1tvipa2 | B156: TIVOLI MONITOR 6 (ITM6) | C156: =VLOOKUP(B156,CMDB_Apps!B:J,9,FALSE) -> TSS-Ops-Support-Observability | D156: Operational | E156: 46069.925 | G156: raz1tvipa2.caremarkrx.net | H156: AIX | I156: PROD | J156: PROD | K156: TIVOLI MONITOR 6 (ITM6) | L156: 10.93.7.68 | M156: none | N156: global | O156: 7.2.0.0
A157: paz1sppanl12v | B157: SpRx 2.0 | C157: =VLOOKUP(B157,CMDB_Apps!B:J,9,FALSE) -> SPRX 2.0 TIER 3 | D157: Operational | E157: 46069.925 | G157: paz1sppanl12v.corp.cvscaremark.com | H157: Red Hat Enterprise Linux Release 8.10 (ootpa) | I157: TEST | J157: PT | K157: SpRx 2.0 | L157: 10.9.62.219 | M157: corp.cvscaremark.com | N157: global | O157: 8.10
A158: paz1sppanl13v | B158: SpRx 2.0 | C158: =VLOOKUP(B158,CMDB_Apps!B:J,9,FALSE) -> SPRX 2.0 TIER 3 | D158: Operational | E158: 46069.925 | G158: paz1sppanl13v.corp.cvscaremark.com | H158: Linux Red Hat | I158: TEST | J158: PT | K158: SpRx 2.0 | L158: 10.9.80.109 | M158: corp.cvscaremark.com | N158: global | O158: 8.10
A159: paz1sppanl16v | B159: SpRx 2.0 | C159: =VLOOKUP(B159,CMDB_Apps!B:J,9,FALSE) -> SPRX 2.0 TIER 3 | D159: Operational | E159: 46069.924 | G159: paz1sppanl16v.corp.cvscaremark.com | H159: Linux Red Hat | I159: TEST | J159: PT | K159: SpRx 2.0 | L159: 10.9.80.124 | M159: corp.cvscaremark.com | N159: global | O159: 8.10
A160: paz1sppanl14v | B160: SpRx 2.0 | C160: =VLOOKUP(B160,CMDB_Apps!B:J,9,FALSE) -> SPRX 2.0 TIER 3 | D160: Operational | E160: 46069.924 | G160: paz1sppanl14v.corp.cvscaremark.com | H160: Linux Red Hat | I160: TEST | J160: PT | K160: SpRx 2.0 | L160: 10.9.80.110 | M160: corp.cvscaremark.com | N160: global | O160: 8.10
A161: paz1sppanl25v | B161: SpRx 2.0 | C161: =VLOOKUP(B161,CMDB_Apps!B:J,9,FALSE) -> SPRX 2.0 TIER 3 | D161: Operational | E161: 46069.924 | G161: paz1sppanl25v.corp.cvscaremark.com | H161: Linux Red Hat | I161: TEST | J161: PT | K161: SpRx 2.0 | L161: 10.9.80.108 | M161: corp.cvscaremark.com | N161: global | O161: 8.10
A162: paz1orapl2v | B162: DISPENSING - SPECIALTY - PPS | C162: =VLOOKUP(B162,CMDB_Apps!B:J,9,FALSE) -> PCW_IT_SpecialtyBackendDispensing_L2Support | D162: Operational | E162: 46069.924 | G162: paz1orapl2v.corp.cvscaremark.com | H162: Linux Red Hat | I162: PROD | J162: PROD | K162: DISPENSING - SPECIALTY - PPS | L162: 10.93.25.40 | M162: corp.cvscaremark.com | N162: global | O162: 7.9
A163: paz1sppranl3v | B163: SpRx 2.0 | C163: =VLOOKUP(B163,CMDB_Apps!B:J,9,FALSE) -> SPRX 2.0 TIER 3 | D163: Operational | E163: 46069.924 | G163: paz1sppranl3v.corp.cvscaremark.com | H163: Linux Red Hat | I163: TEST | J163: PT | K163: SpRx 2.0 | L163: 10.9.80.120 | M163: corp.cvscaremark.com | N163: global | O163: 8.10
... A219: paz1nexapl2v | B219: NexusLinks-CVS | C219: =VLOOKUP(B219,CMDB_Apps!B:J,9,FALSE) -> DevOps Engineering | D219: Operational | E219: 46069.916 | G219: paz1nexapl2v.corp.cvscaremark.com | H219: Linux Red Hat | I219: PROD | J219: PROD | K219: NexusLinks-CVS | L219: 10.124.64.161 | M219: corp.cvscaremark.com | N219: global | O219: 7.9
A220: paz1sprdn1r1 | C220: =VLOOKUP(B220,CMDB_Apps!B:J,9,FALSE) -> #N/A | D220: Operational | E220: 46069.916 | G220: paz1sprdn1r1.corp.cvscaremark.com | H220: Linux Red Hat | I220: TEST | J220: TEST | L220: 10.9.80.67 | M220: corp.cvscaremark.com | N220: global | O220: 7.9
A221: paz1spslpl3v | B221: SPLUNK - PCI | C221: =VLOOKUP(B221,CMDB_Apps!B:J,9,FALSE) -> TSS-Ops-Support-Observability | D221: Operational | E221: 46069.916 | G221: paz1spslpl3v.corp.cvscaremark.com | H221: Red Hat Enterprise Linux Server Release 7.9 (maipo) | I221: PROD | J221: PROD | K221: SPLUNK - PCI | L221: 10.93.22.118 | M221: corp.cvscaremark.com | N221: global | O221: 7.9
A222: paz1sppfdnl3v | B222: SpRx 2.0 | C222: =VLOOKUP(B222,CMDB_Apps!B:J,9,FALSE) -> SPRX 2.0 TIER 3 | D222: Operational | E222: 46069.916 | G222: paz1sppfdnl3v.corp.cvscaremark.com | H222: Linux Red Hat | I222: TEST | J222: PT | K222: SpRx 2.0 | L222: 10.9.80.119 | M222: corp.cvscaremark.com | N222: global | O222: 8.10
A223: paz1sphfpl12v | B223: SPLUNK - PCI | C223: =VLOOKUP(B223,CMDB_Apps!B:J,9,FALSE) -> TSS-Ops-Support-Observability | D223: Operational | E223: 46069.916 | G223: paz1sphfpl12v.caremarkrx.net | H223: Linux Red Hat | I223: PROD | J223: PROD | K223: SPLUNK - PCI | L223: 10.93.12.19 | M223: corp.cvscaremark.com | N223: global | O223: 8.10
A224: paz1mixppl11v | B224: Data Reporting Portal | C224: =VLOOKUP(B224,CMDB_Apps!B:J,9,FALSE) -> 0 | D224: Operational | E224: 46069.916 | G224: paz1mixppl11v.corp.cvscaremark.com | H224: Linux Red Hat | I224: PROD | J224: PROD | K224: Data Reporting Portal | L224: 10.249.152.62 | M224: corp.cvscaremark.com | N224: global | O224: 8.10
A225: paz1nexapl1v | B225: NexusPro, NexusLinks-CVS | C225: =VLOOKUP(B225,CMDB_Apps!B:J,9,FALSE) -> #N/A | D225: Operational | E225: 46069.916 | G225: paz1nexapl1v.corp.cvscaremark.com | H225: Linux Red Hat | I225: PROD | J225: PROD | K225: NexusPro, NexusLinks-CVS | L225: 10.124.64.156 | M225: corp.cvscaremark.com | N225: global | O225: 7.9
A226: pri2tsnwpl1v | B226: BCD-CM | C226: =VLOOKUP(B226,CMDB_Apps!B:J,9,FALSE) -> 0 | D226: Operational | E226: 46069.916 | G226: pri2tsnwpl1v.corp.cvscaremark.com | H226: Linux Red Hat | I226: DR | J226: DR | K226: BCD-CM | L226: 10.228.164.56 | M226: corp.cvscaremark.com | N226: global | O226: 8.10
A227: paz1mixppl13v | B227: Data Reporting Portal | C227: =VLOOKUP(B227,CMDB_Apps!B:J,9,FALSE) -> 0 | D227: Operational | E227: 46069.916 | G227: paz1mixppl13v.corp.cvscaremark.com | H227: Linux Red Hat | I227: PROD | J227: PROD | K227: Data Reporting Portal | L227: 10.249.152.63 | M227: corp.cvscaremark.com | N227: global | O227: 8.10
A228: ppa2sandpl1v | B228: DISPENSING - SPECIALTY - SANITAS | C228: =VLOOKUP(B228,CMDB_Apps!B:J,9,FALSE) -> PCW_IT_SpecialtyBackendDispensing_L2Support | D228: Operational | E228: 46069.916 | G228: ppa2sandpl1v.corp.cvscaremark.com | H228: Linux Red Hat | I228: PROD | J228: PROD | K228: DISPENSING - SPECIALTY - SANITAS | L228: 10.81.32.49 | M228: corp.cvscaremark.com | N228: global | O228: 8.10
A229: pri2mixppl14v | B229: Data Reporting Portal | C229: =VLOOKUP(B229,CMDB_Apps!B:J,9,FALSE) -> 0 | D229: Operational | E229: 46069.916 | G229: pri2mixppl14v.corp.cvscaremark.com | H229: Linux Red Hat | I229: PROD | J229: PROD | K229: Data Reporting Portal | L229: 10.249.24.57 | M229: corp.cvscaremark.com | N229: global | O229: 8.10
A230: ptx25mrdpl1v | B230: DISPENSING - SPECIALTY - SANITAS | C230: =VLOOKUP(B230,CMDB_Apps!B:J,9,FALSE) -> PCW_IT_SpecialtyBackendDispensing_L2Support | D230: Operational | E230: 46069.916 | G230: ptx25mrdpl1v.corp.cvscaremark.com | H230: Linux Red Hat | I230: PROD | J230: PROD | K230: DISPENSING - SPECIALTY - SANITAS | L230: 10.30.33.51 | M230: corp.cvscaremark.com | N230: global | O230: 8.10
A231: rri1otcdpl1v | B231: OTC HEALTH SOLUTIONS | C231: =VLOOKUP(B231,CMDB_Apps!B:J,9,FALSE) -> PCW-Technology-OTCHS | D231: Operational | E231: 46069.916 | G231: rri1otcdpl1v.corp.cvscaremark.com | H231: Linux Red Hat | I231: PROD | J231: PROD | K231: OTC HEALTH SOLUTIONS | L231: 10.18.148.71 | M231: corp.cvscaremark.com | N231: global | O231: 7.9
A232: paz1sppfdnl2v | B232: SpRx 2.0 | C232: =VLOOKUP(B232,CMDB_Apps!B:J,9,FALSE) -> SPRX 2.0 TIER 3 | D232: Operational | E232: 46069.916 | G232: paz1sppfdnl2v.corp.cvscaremark.com | H232: Linux Red Hat | I232: TEST | J232: PT | K232: SpRx 2.0 | L232: 10.9.80.118 | M232: corp.cvscaremark.com | N232: global | O232: 8.10
... A338: paz1smrppl11v | B338: ENTERPRISE SITEMINDER | C338: =VLOOKUP(B338,CMDB_Apps!B:J,9,FALSE) -> 0 | D338: Operational | E338: 46069.792 | G338: paz1smrppl11v.corp.cvscaremark.com | H338: Linux Red Hat | I338: PROD | J338: PROD | K338: ENTERPRISE SITEMINDER | L338: 10.249.148.114 | M338: corp.cvscaremark.com | N338: global | O338: 8.10
A339: paz1vorpl1p | B339: ECCR VORDEL | C339: =VLOOKUP(B339,CMDB_Apps!B:J,9,FALSE) -> 0 | D339: Operational | E339: 46069.792 | G339: paz1vorpl1p.caremarkrx.net | H339: Linux Red Hat | I339: PROD | J339: PROD | K339: ECCR VORDEL | L339: 10.93.6.122 | N339: global | O339: 6.10
A340: paz1sappdpl1v | B340: SAP PIPO (PBM) | C340: =VLOOKUP(B340,CMDB_Apps!B:J,9,FALSE) -> 0 | D340: Operational | E340: 46069.535 | G340: paz1sappdpl1v.corp.cvscaremark.com | H340: Linux Red Hat | I340: PROD | J340: PROD | K340: SAP PIPO (PBM) | L340: 10.93.34.221 | M340: corp.cvscaremark.com | N340: global | O340: 7.9
A341: prdora4a | B341: SERENA DIMENSIONS, POLICY & PROCEDURE PORTAL | C341: =VLOOKUP(B341,CMDB_Apps!B:J,9,FALSE) -> #N/A | D341: Operational | E341: 46069.535 | G341: prdora4a.caremarkrx.net | H341: AIX | I341: PROD | J341: PROD | K341: SERENA DIMENSIONS, POLICY & PROCEDURE PORTAL | L341: 204.99.33.132 | M341: caremarkrx.net | N341: global | O341: 7.2.0.0
A342: paz1ppsdpl3v | B342: DISPENSING - PPS, DISPENSING - TRISTAR | C342: =VLOOKUP(B342,CMDB_Apps!B:J,9,FALSE) -> #N/A | D342: Operational | E342: 46069.534 | G342: paz1ppsdpl3v.caremarkrx.net | H342: Linux Red Hat | I342: PROD | J342: PROD | K342: DISPENSING - PPS, DISPENSING - TRISTAR | L342: 10.93.77.99 | M342: corp.cvscaremark.com | N342: global | O342: 7.9
A343: paz1sppapl7v | B343: SpRx 2.0 | C343: =VLOOKUP(B343,CMDB_Apps!B:J,9,FALSE) -> SPRX 2.0 TIER 3 | D343: Operational | E343: 46068.968 | G343: paz1sppapl7v.corp.cvscaremark.com | H343: Linux Red Hat | I343: PROD | J343: PROD | K343: SpRx 2.0 | L343: 10.124.65.69 | M343: corp.cvscaremark.com | N343: global | O343: 8.10
A344: paz1sppapl8v | B344: SpRx 2.0 | C344: =VLOOKUP(B344,CMDB_Apps!B:J,9,FALSE) -> SPRX 2.0 TIER 3 | D344: Operational | E344: 46068.968 | G344: paz1sppapl8v.corp.cvscaremark.com | H344: Linux Red Hat | I344: PROD | J344: PROD | K344: SpRx 2.0 | L344: 10.124.65.70 | M344: corp.cvscaremark.com | N344: global | O344: 8.10
A345: paz1smrppl13v | B345: ENTERPRISE SITEMINDER | C345: =VLOOKUP(B345,CMDB_Apps!B:J,9,FALSE) -> 0 | D345: Operational | E345: 46068.968 | G345: paz1smrppl13v.corp.cvscaremark.com | H345: Linux Red Hat | I345: PROD | J345: PROD | K345: ENTERPRISE SITEMINDER | L345: 10.249.152.101 | M345: corp.cvscaremark.com | N345: global | O345: 8.10
A346: paz1sppapl39v | B346: SpRx 2.0 | C346: =VLOOKUP(B346,CMDB_Apps!B:J,9,FALSE) -> SPRX 2.0 TIER 3 | D346: Operational | E346: 46068.968 | G346: paz1sppapl39v.corp.cvscaremark.com | H346: Linux Red Hat | I346: PROD | J346: PROD | K346: SpRx 2.0 | L346: 10.249.152.80 | M346: corp.cvscaremark.com | N346: global | O346: 7.9
A347: paz1sppcpl13v | B347: SpRx 2.0 | C347: =VLOOKUP(B347,CMDB_Apps!B:J,9,FALSE) -> SPRX 2.0 TIER 3 | D347: Operational | E347: 46068.968 | G347: paz1sppcpl13v.corp.cvscaremark.com | H347: Linux Red Hat | I347: PROD | J347: PROD | K347: SpRx 2.0 | L347: 10.249.152.83 | M347: corp.cvscaremark.com | N347: global | O347: 8.10
A348: paz1smrppl10v | B348: ENTERPRISE SITEMINDER | C348: =VLOOKUP(B348,CMDB_Apps!B:J,9,FALSE) -> 0 | D348: Operational | E348: 46068.968 | G348: paz1smrppl10v.corp.cvscaremark.com | H348: Linux Red Hat | I348: PROD | J348: PROD | K348: ENTERPRISE SITEMINDER | L348: 10.249.152.100 | M348: corp.cvscaremark.com | N348: global | O348: 8.10
A349: paz1sppapl1v | B349: SpRx 2.0 | C349: =VLOOKUP(B349,CMDB_Apps!B:J,9,FALSE) -> SPRX 2.0 TIER 3 | D349: Operational | E349: 46068.968 | G349: paz1sppapl1v.corp.cvscaremark.com | H349: Linux Red Hat | I349: PROD | J349: PROD | K349: SpRx 2.0 | L349: 10.124.65.63 | M349: corp.cvscaremark.com | N349: global | O349: 8.10
A350: paz1sppapl38v | B350: SpRx 2.0 | C350: =VLOOKUP(B350,CMDB_Apps!B:J,9,FALSE) -> SPRX 2.0 TIER 3 | D350: Operational | E350: 46068.968 | G350: paz1sppapl38v.corp.cvscaremark.com | H350: Linux Red Hat | I350: PROD | J350: PROD | K350: SpRx 2.0 | L350: 10.249.148.95 | M350: corp.cvscaremark.com | N350: global | O350: 7.9
A351: paz1sppgapl2v | B351: SpRx 2.0 | C351: =VLOOKUP(B351,CMDB_Apps!B:J,9,FALSE) -> SPRX 2.0 TIER 3 | D351: Operational | E351: 46068.968 | G351: paz1sppgapl2v.corp.cvscaremark.com | H351: Linux Red Hat | I351: PROD | J351: PROD | K351: SpRx 2.0 | L351: 10.124.65.51 | M351: corp.cvscaremark.com | N351: global | O351: 8.10
... A440: paz1cscwpl2v | B440: Unclaimed Property | C440: =VLOOKUP(B440,CMDB_Apps!B:J,9,FALSE) -> 0 | D440: Operational | E440: 46068.792 | G440: paz1cscwpl2v.corp.cvscaremark.com | H440: Linux Red Hat | I440: PROD | J440: PROD | K440: Unclaimed Property | L440: 10.123.132.172 | M440: corp.cvscaremark.com | N440: global | O440: 7.9
A441: rac4ewsapl16v | C441: =VLOOKUP(B441,CMDB_Apps!B:J,9,FALSE) -> #N/A | D441: Operational | E441: 46068.792 | G441: rac4ewsapl16v.corp.cvscaremark.com | H441: Linux Red Hat | I441: PROD | J441: PROD | L441: 10.83.129.185 | M441: corp.cvscaremark.com | N441: global | O441: 8.10
A442: rac2ewsapl16v | B442: EWS-ERE | C442: =VLOOKUP(B442,CMDB_Apps!B:J,9,FALSE) -> RXC - APP SUPPORT | D442: Operational | E442: 46068.792 | G442: rac2ewsapl16v.corp.cvscaremark.com | H442: Linux Red Hat | I442: PROD | J442: PROD | K442: EWS-ERE | L442: 10.83.53.245 | M442: corp.cvscaremark.com | N442: global | O442: 8.10
A443: rac2ewsapl17v | C443: =VLOOKUP(B443,CMDB_Apps!B:J,9,FALSE) -> #N/A | D443: Operational | E443: 46068.792 | G443: rac2ewsapl17v.corp.cvscaremark.com | H443: Linux Red Hat | I443: PROD | J443: PROD | L443: 10.83.53.246 | M443: corp.cvscaremark.com | N443: global | O443: 8.10
A444: paz1apidpl3v | B444: VORDEL | C444: =VLOOKUP(B444,CMDB_Apps!B:J,9,FALSE) -> 0 | D444: Operational | E444: 46068.792 | G444: paz1apidpl3v.caremarkrx.net | H444: Linux Red Hat | I444: PROD | J444: PROD | K444: VORDEL | L444: 10.124.188.71 | M444: corp.cvscaremark.com | N444: global | O444: 8.10
A445: rri1rxdupl16v | B445: RxConnect | C445: =VLOOKUP(B445,CMDB_Apps!B:J,9,FALSE) -> Data Network Operations | D445: Operational | E445: 46068.792 | G445: rri1rxdupl16v.corp.cvscaremark.com | H445: Linux Red Hat | I445: PROD | J445: PROD | K445: RxConnect | L445: 10.228.157.52 | M445: corp.cvscaremark.com | N445: global | O445: 8.10
A446: paz1apidpl2v | B446: VORDEL | C446: =VLOOKUP(B446,CMDB_Apps!B:J,9,FALSE) -> 0 | D446: Operational | E446: 46068.792 | G446: paz1apidpl2v.caremarkrx.net | H446: Linux Red Hat | I446: PROD | J446: PROD | K446: VORDEL | L446: 10.124.188.70 | M446: corp.cvscaremark.com | N446: global | O446: 8.10
A447: paz1apidpl1v | B447: VORDEL | C447: =VLOOKUP(B447,CMDB_Apps!B:J,9,FALSE) -> 0 | D447: Operational | E447: 46068.792 | G447: paz1apidpl1v.caremarkrx.net | H447: Linux Red Hat | I447: PROD | J447: PROD | K447: VORDEL | L447: 10.124.188.69 | M447: corp.cvscaremark.com | N447: global | O447: 8.10
A448: paz1spslpl2v | B448: SPLUNK - PCI | C448: =VLOOKUP(B448,CMDB_Apps!B:J,9,FALSE) -> TSS-Ops-Support-Observability | D448: Operational | E448: 46068.792 | G448: paz1spslpl2v | H448: RHEL7.9 | I448: PROD | J448: PROD | K448: SPLUNK - PCI | L448: 10.93.22.117 | M448: corp.cvscaremark.com | N448: global
A449: paz1epsdpl2v | B449: DISPENSING ENTERPRISE APPS | C449: =VLOOKUP(B449,CMDB_Apps!B:J,9,FALSE) -> PCW_IT_MailBackendDispensing_L2Support | D449: Operational | E449: 46068.792 | G449: paz1epsdpl2v.corp.cvscaremark.com | H449: Linux Red Hat | I449: PROD | J449: PROD | K449: DISPENSING ENTERPRISE APPS | L449: 10.93.22.254 | M449: corp.cvscaremark.com | N449: global | O449: 8.10
A450: paz1icewpl3v | B450: ICE-T | C450: =VLOOKUP(B450,CMDB_Apps!B:J,9,FALSE) -> DIGITAL PS TIER TWO ICE | D450: Operational | E450: 46068.792 | G450: paz1icewpl3v.corp.cvscaremark.com | H450: RHEL7.9 | I450: PROD | J450: PROD | K450: ICE-T | L450: 10.123.132.169 | M450: corp.cvscaremark.com | N450: global
A451: paz1icewpl4v | B451: ICE-T | C451: =VLOOKUP(B451,CMDB_Apps!B:J,9,FALSE) -> DIGITAL PS TIER TWO ICE | D451: Operational | E451: 46068.792 | G451: paz1icewpl4v | H451: RHEL7.9 | I451: PROD | J451: PROD | K451: ICE-T | L451: 10.123.132.170 | M451: corp.cvscaremark.com | N451: global
A452: paz1icewpl2v | B452: ICE-T | C452: =VLOOKUP(B452,CMDB_Apps!B:J,9,FALSE) -> DIGITAL PS TIER TWO ICE | D452: Operational | E452: 46068.792 | G452: paz1icewpl2v.corp.cvscaremark.com | H452: RHEL7.9 | I452: PROD | J452: PROD | K452: ICE-T | L452: 10.123.132.168 | M452: corp.cvscaremark.com | N452: global
A453: paz1icewpl1v | B453: ICE-T | C453: =VLOOKUP(B453,CMDB_Apps!B:J,9,FALSE) -> DIGITAL PS TIER TWO ICE | D453: Operational | E453: 46068.792 | G453: paz1icewpl1v.corp.cvscaremark.com | H453: Linux Red Hat | I453: PROD | J453: PROD | K453: ICE-T | L453: 10.123.132.167 | M453: corp.cvscaremark.com | N453: global | O453: 7.9
A454: paz1tljapl2v | B454: Specialty Pharmacy Order Management | C454: =VLOOKUP(B454,CMDB_Apps!B:J,9,FALSE) -> SPOMS | D454: Operational | E454: 46068.792 | G454: paz1tljapl2v.corp.cvscaremark.com | H454: Linux Red Hat | I454: PROD | J454: PROD | K454: Specialty Pharmacy Order Management | L454: 10.123.134.231 | M454: corp.cvscaremark.com | N454: global | O454: 8.10
A455: paz1cscwsl1v | B455: Unclaimed Property | C455: =VLOOKUP(B455,CMDB_Apps!B:J,9,FALSE) -> 0 | D455: Operational | E455: 46068.792 | G455: paz1cscwsl1v.corp.cvscaremark.com | H455: Linux Red Hat | I455: TEST | J455: PROD | K455: Unclaimed Property | L455: 10.123.130.198 | M455: corp.cvscaremark.com | N455: global | O455: 7.9
A456: rri1rxdupl15v | B456: RxConnect | C456: =VLOOKUP(B456,CMDB_Apps!B:J,9,FALSE) -> Data Network Operations | D456: Operational | E456: 46068.792 | G456: rri1rxdupl15v.cvs.com | H456: Linux Red Hat | I456: PROD | J456: PROD | K456: RxConnect | L456: 10.228.157.51 | M456: corp.cvscaremark.com | N456: global | O456: 8.10
A457: paz1sppgpl11v | B457: SpRx 2.0 | C457: =VLOOKUP(B457,CMDB_Apps!B:J,9,FALSE) -> SPRX 2.0 TIER 3 | D457: Operational | E457: 46068.792 | G457: paz1sppgpl11v.corp.cvscaremark.com | H457: RHEL7.9 | I457: PROD | J457: PROD | K457: SpRx 2.0 | L457: 10.93.135.237 | M457: corp.cvscaremark.com | N457: global
A458: raz1mqqarl10v | B458: MQ SERIES, MQ | C458: =VLOOKUP(B458,CMDB_Apps!B:J,9,FALSE) -> #N/A | D458: Operational | E458: 46068.792 | G458: raz1mqqarl10v.corp.cvscaremark.com | H458: Linux Red Hat | I458: DR | J458: DR | K458: MQ SERIES, MQ | L458: 10.249.152.60 | M458: corp.cvscaremark.com | N458: global | O458: 7.9
A459: paz1sivapl14v | B459: Nuance Insights Specialty, Specialty IVR | C459: =VLOOKUP(B459,CMDB_Apps!B:J,9,FALSE) -> #N/A | D459: Operational | E459: 46068.792 | G459: paz1sivapl14v.corp.cvscaremark.com | H459: RHEL7.9 | I459: PROD | J459: PROD | K459: Nuance Insights Specialty, Specialty IVR | L459: 10.93.165.50 | M459: corp.cvscaremark.com | N459: global
A460: rri1rxdupl13v | B460: RxConnect | C460: =VLOOKUP(B460,CMDB_Apps!B:J,9,FALSE) -> Data Network Operations | D460: Operational | E460: 46068.792 | G460: rri1rxdupl13v.cvs.com | H460: Linux Red Hat | I460: PROD | J460: PROD | K460: RxConnect | L460: 10.228.157.49 | M460: corp.cvscaremark.com | N460: global | O460: 8.10
A461: paz1sppcpl11v | B461: SpRx 2.0 | C461: =VLOOKUP(B461,CMDB_Apps!B:J,9,FALSE) -> SPRX 2.0 TIER 3 | D461: Operational | E461: 46068.792 | G461: paz1sppcpl11v.corp.cvscaremark.com | H461: RHEL7.9 | I461: PROD | J461: PROD | K461: SpRx 2.0 | L461: 10.93.135.165 | M461: corp.cvscaremark.com | N461: global
A462: paz1sppgtl10v | B462: SpRx 2.0 | C462: =VLOOKUP(B462,CMDB_Apps!B:J,9,FALSE) -> SPRX 2.0 TIER 3 | D462: Operational | E462: 46068.792 | G462: paz1sppgtl10v.corp.cvscaremark.com | H462: Linux Red Hat | I462: PROD | J462: CTE | K462: SpRx 2.0 | L462: 10.94.6.116 | M462: corp.cvscaremark.com | N462: global | O462: 8.10
A463: paz1dytapl11v | B463: SpRx 1.0 | C463: =VLOOKUP(B463,CMDB_Apps!B:J,9,FALSE) -> SPRX 1.0 | D463: Operational | E463: 46068.792 | G463: paz1dytapl11v.corp.cvscaremark.com | H463: RHEL8.10 | I463: PROD | J463: PROD | K463: SpRx 1.0 | L463: 10.217.239.32 | M463: corp.cvscaremark.com | N463: global
A464: paz1rtldtl1v | B464: PSS Digital Microservices | C464: =VLOOKUP(B464,CMDB_Apps!B:J,9,FALSE) -> DIGITAL PS TIER THREE PBM | D464: Operational | E464: 46068.792 | G464: paz1rtldtl1v.corp.cvscaremark.com | H464: Linux Red Hat | I464: TEST | J464: CTE | K464: PSS Digital Microservices | L464: 10.94.53.230 | M464: corp.cvscaremark.com | N464: global | O464: 7.9
A465: paz1apipl5p | B465: VORDEL | C465: =VLOOKUP(B465,CMDB_Apps!B:J,9,FALSE) -> 0 | D465: Operational | E465: 46068.792 | G465: paz1apipl5p.corp.cvscaremark.com | H465: RHEL7.9 | I465: PROD | J465: PROD | K465: VORDEL | L465: 10.123.202.227 | M465: corp.cvscaremark.com | N465: global
A466: paz1epsdpl1v | B466: DISPENSING ENTERPRISE APPS | C466: =VLOOKUP(B466,CMDB_Apps!B:J,9,FALSE) -> PCW_IT_MailBackendDispensing_L2Support | D466: Operational | E466: 46068.792 | G466: paz1epsdpl1v.corp.cvscaremark.com | H466: Linux Red Hat | I466: PROD | J466: PROD | K466: DISPENSING ENTERPRISE APPS | L466: 10.93.22.253 | M466: corp.cvscaremark.com | N466: global | O466: 8.10
A467: paz1apipl6p | B467: VORDEL | C467: =VLOOKUP(B467,CMDB_Apps!B:J,9,FALSE) -> 0 | D467: Operational | E467: 46068.792 | G467: paz1apipl6p.corp.cvscaremark.com | H467: RHEL7.9 | I467: PROD | J467: PROD | K467: VORDEL | L467: 10.123.202.228 | M467: corp.cvscaremark.com | N467: global
A468: paz1bnbdpl1a | B468: BENEFIT BUILDER, BMA, Formulary Management System, BENEFIT CONSULTANT, CAG services, Clinical Solutions Data Hub, Formulary Alternatives, Formulary and Wareshouse Extracts | C468: =VLOOKUP(B468,CMDB_Apps!B:J,9,FALSE) -> #N/A | D468: Operational | E468: 46068.792 | G468: paz1bnbdpl1a.corp.cvscaremark.com | H468: RHEL7.9 | I468: PROD | J468: PROD | K468: BENEFIT BUILDER, BMA, Formulary Management System, BENEFIT CONSULTANT, CAG services, Clinical Solutions Data Hub, Formulary Alternatives, Formulary and Wareshouse Extracts | L468: 10.217.160.130 | M468: corp.cvscaremark.com | N468: global
...

Sheet CMDB_Apps
A1: Application ID | B1: Name | C1: Status | D1: Business criticality | E1: Business Unit | F1: Last updated by | G1: Business owner | H1: Operational Owner | I1: Technical Owner | J1: Support group | K1: Risk Tier | L1: Risk indicator | M1: Last change applied date | N1: Description | O1: Target Business Application | P1: Business process | Q1: Application type | R1: Architecture type | S1: Install type | T1: Life Cycle Stage Status | U1: Life Cycle Stage | V1: Technology stack | W1: User base | X1: Platform | Y1: Application Instance ID | Z1: Emergency tier | AA1: Data classification | AB1: Certified | AC1: Model ID
B2: myPBM GitHub Actions Pipeline | C2: Production | E2: PSS Pharmacy Service Segment | F2: system | G2: Dwarakanath Raghunathan | H2: Dwarakanath Raghunathan | I2: Richard Berktold | J2: myPBM_SRE | N2: Github Actions Build and Deploy Workflows implemented by the myPBM SRE team to replace existing Jenkins pipelines | Q2: Homegrown | S2: PaaS | AB2: FALSE | AC2: myPBM GitHub Actions Pipeline
A3: 2349 | B3: .Net Solutions | C3: Production | E3: HCB | F3: system | G3: Jinex Thomas Thandiakkal | H3: Jinex Thomas Thandiakkal | I3: Neeta Myageri | J3: L1.0-Framework Services Support | K3: Low Risk | N3: FS .NET products and solutions | Q3: Homegrown | S3: On Premise | Y3: OI-D52531D80E71457995771FE288B72A25 | AA3: Unclassified | AB3: FALSE | AC3: .Net Solutions
B4: 1E Platform | C4: Production | E4: ISTS | F4: system | G4: Joseph Lombardi | H4: Joseph Lombardi | I4: Sarah Thomas | K4: Low Risk | N4: Provides automated, real-time configuration to workstation clients. Provides client system details. Also used for Nomad single-site download information | Q4: COTS | S4: IaaS | AA4: Restricted | AB4: FALSE | AC4: 1E Platform
B5: 1E Shopping | C5: Production | E5: ISTS | F5: system | G5: Joseph Lombardi | H5: Joseph Lombardi | I5: Sarah Thomas | K5: Low Risk | N5: Shopping is used as a application ordering solution that can be itegrated with Service Now. It provides employees with an automated portal service that can fulfill requests for apps, new devices and equipment such as desks for home working or anything | Q5: COTS | S5: IaaS | AA5: Unclassified | AB5: FALSE | AC5: 1E Shopping
B6: 340B Data Products | C6: Production | F6: system | G6: Ryan Rowley | H6: Jose Vinay Chalissery | I6: Roshan Kumar | J6: 340B_Data_Products_change_mgnmt | K6: Low Risk | N6: Consolidated 340B data from the enterprise to enable reporting and ad hoc analyses related to the 340B program. | Q6: Homegrown | S6: Hybrid | AA6: Confidential | AB6: FALSE | AC6: 340B Data Products
B7: 340B Data Products Retail | C7: Production | E7: PSS Pharmacy Service Segment | F7: system | G7: Jose Vinay Chalissery | H7: Kamini Malhari Bokefode | I7: Aswani Gollakota | J7: three_forty_b_scheduling | N7: This is a set of Analytical engineering products created for 340 business for retail line of business. This includes products such as retail 340B feed, retail opportunity, retail outcomes etc. | Q7: COTS | S7: SaaS | AB7: FALSE | AC7: 340B Data Products Retail
B8: 340B Smart | C8: Production | E8: HCB | F8: system | G8: Darren West | H8: David Sterzel | I8: Micah Mcnelly | K8: High Risk | N8: 340b Smart Automatically splits and tracks replenishment orders for eligible medications into multiple accounts (340B, GPO, WAC.) | Q8: Homegrown | S8: IaaS | AA8: Confidential | AB8: FALSE | AC8: 340B Smart
A9: 2145 | B9: 3rd Party Feeder | C9: Production | E9: HCB | F9: system | G9: Alex Sawa | H9: Srideepthi Vejendla | I9: Viatcheslav Mironenko | J9: L1.0-SIMPLE STEPS APP SUPPORT | K9: Low Risk | N9: This is an application that is used by SimpleSteps to receive status about Miavita program completions and starts. This application also provides the Webservices for SSHL/PHR domain. | Q9: Homegrown | S9: On Premise | Y9: OI-D8506491C204445A9C3AEBB82361A2F6 | AA9: Confidential | AB9: FALSE | AC9: 3rd Party Feeder
B10: 90 DAY & MTM | C10: Production | E10: Retail | F10: system | G10: Lidia Thomas | H10: Lidia Thomas | I10: Alexander Sahakian | K10: Low Risk | N10: 90 Day Medication Therapy Management. RxDW provides 90 Day (Accept/Decline) Disposition details to RxConnect using 90-day(RxOutreach) application. | Q10: Homegrown | S10: Hybrid | AA10: Confidential | AB10: FALSE | AC10: 90 DAY & MTM
B11: A&BC Life Inusurance | C11: Production | E11: Corporate | F11: 2646189 | G11: Aamir Shibli | H11: Prabhu Ramakrishnan | I11: Prabhu Ramakrishnan | J11: EDML SRE Prod Support | N11: The A&BC data monetization and strategy team is bringing a product to market that will allow Life Insurance companies/brokers the ability to “ping” CVS Health with demographic information in order to receive back individual patient medical history; including but not limited to, health insurance claims/eligibility roster, Caremark PBM claims/eligibility roster, retail pharmacy dispensement, medical encounters at the MinuteClinic, etc. Our life insurance partners will be able to ‘ping’ the CVS data sources relative to their data needs. | Q11: Homegrown | S11: DaaS | AB11: FALSE | AC11: A&BC Life Inusurance
B12: A11Y Media | C12: Production | E12: SS Shared Services | F12: system | G12: Ryan Brady | H12: Matthew Ferrone | I12: Cory Joseph | J12: Corp-Digital-A11Y-L2 Support | N12: Use of GCP AI Vertex Media Studio to create internal marketing and educational videos for designers and engineers. | Q12: COTS | S12: SaaS | AB12: FALSE | AC12: A11Y Media
B13: A1A_Reporting | C13: Production | E13: HCB | F13: system | G13: Teresa Mitchelson | H13: Joseph Leathlean | I13: Joseph Leathlean | K13: Low Risk | N13: A1A Reporting | Q13: COTS | S13: Hybrid | AA13: Restricted | AB13: FALSE | AC13: A1A_Reporting
B14: A4LEvents | C14: Production | E14: Health Care Benefits | F14: system | G14: Ellen Chamberlain | H14: Krishna Pyneni | I14: Shrivallabha Deshpande | K14: Low Risk | N14: This component will process member events emitted by Enterprise Patient Hub (EPH) to keep ACCOUNT FOR LIFE table updated with latest information. | Q14: Homegrown | S14: On Premise | AA14: Proprietary | AB14: FALSE | AC14: A4LEvents
A15: 4209 | B15: AAD Application proxy | C15: Production | E15: ISTS | F15: system | G15: Eric Kovacs | H15: Anthony Vasi | I15: Gregory Nichols | K15: Low Risk | N15: Azure AD Application Proxy provides a simple, secure, and cost-effective remote access solution to all your on-premises applications. | Q15: COTS | S15: On Premise | Y15: OI-E3EFEF2FEE8340858DC14B4D5FEAF101 | AA15: Unclassified | AB15: FALSE | AC15: AAD Application proxy
B16: AAP-HCB-POA-COB-ANALYTICS | C16: Production | E16: HCB | F16: system | G16: Patricia Serio | H16: Narayan Sahasranamaiyer | I16: Kuntal Ghosh | J16: Claims Analytics Data Engineering | N16: Coordination of Benefits (COB) is to determine the correct order of benefits for members with coverage on multiple insurance plans across Commercial ,Medicare and Medicaid LOBs | Q16: Homegrown | S16: PaaS | AB16: FALSE | AC16: AAP-HCB-POA-COB-ANALYTICS
B17: AAP-HCB-POA-FWA-ANALYTICS | C17: Production | E17: HCB | F17: system | G17: Patricia Serio | H17: Seema Yadav | I17: Kuntal Ghosh | J17: Claims Analytics Data Engineering | N17: FWA: Program to detect Provider fraud waste and abuse. like provider billing for services never rendered or misrepresenting a patient's condition to get payment. Over-utilization of services, such as using more expensive treatments or tests than necessary. Excessive charging or incorrect billing. | Q17: Homegrown | S17: PaaS | AB17: FALSE | AC17: AAP-HCB-POA-FWA-ANALYTICS
A18: 2483 | B18: AAS Billing/AR | C18: Production | E18: HCB | F18: 2638821 | G18: Darlene Malenfant | H18: Mario Quiroga | I18: David Stiano | J18: L1.0-KB AAS APP SUPPORT | K18: Medium Risk | N18: Supports legacy Billing and remittance for fully insured customers. | Q18: Homegrown | S18: On Premise | Y18: OI-6D718BA78F1D4069ADD781D2F43F536B | AA18: Restricted | AB18: FALSE | AC18: AAS Billing/AR
B19: AAS Product Screen Tool | C19: Production | E19: HCB | F19: system | G19: Kelly McClellan | H19: April Isenberg | I19: Christopher Loughlin | J19: L1.0-KB AAS APP SUPPORT | K19: Low Risk | N19: Service Plan Sponsors | Q19: Homegrown | S19: On Premise | AA19: Unclassified | AB19: FALSE | AC19: AAS Product Screen Tool
B20: Ab Initio Aetna | C20: Production | E20: HCB | F20: 9857522 | G20: Jason Ricapito | H20: Kurt Holever | I20: Kurt Holever | J20: HCB-IT-Ab Initio HCB-L2 Technical Support | K20: Low Risk | N20: Ab Initio provides the most powerful data processing platform available. It can process complex enterprise data using sophisticated business logic at any scale. The applications are built graphically and can run within a batch, streaming, in-memory, or microservice architecture. High performance, end-to-end applications run in parallel and are distributed across containers or networks of different servers. It supports distributed checkpoint restart with application monitoring and alerting. At runtime, the platform adapts to changes in the data formats, rules, and infrastructure, providing a new level of agility. | Q20: COTS | S20: IaaS | AA20: Unclassified | AB20: FALSE | AC20: Ab Initio Aetna
B21: ABBYY FineReader PDF | C21: Production | E21: ISTS | F21: system | G21: Sarah Thomas | H21: David Ottavi | I21: David Ottavi | J21: Desktop Support | K21: Low Risk | N21: Abbyy Fine Reader is an OCR (Optical Character Recognition) application primarily used to edit incoming provider fax on patient information and is replacing another Microsoft OCR product (MODI) | Q21: COTS | S21: On Premise | AA21: Unclassified | AB21: FALSE | AC21: ABBYY FineReader PDF
B22: ABC CADL GWTH Analytics | C22: Production | E22: HCB | F22: 2646189 | G22: Fabio Casadio | H22: Frederick Kirwin | I22: Frederick Kirwin | K22: Low Risk | N22: This application supports exploratory data science work within A&BC, under the Care Delivery and Growth Analytics vertical. | Q22: Homegrown | S22: IaaS | AA22: Confidential | AB22: FALSE | AC22: ABC CADL GWTH Analytics
B23: ABC CDA MC Data Science | C23: Production | E23: HCB | F23: 2646189 | G23: Fabio Casadio | H23: Frederick Kirwin | I23: Frederick Kirwin | K23: Medium Risk | N23: This application supports exploratory data science work within A&BC, under the Clinical Delivery Analytics vertical. | Q23: Homegrown | S23: IaaS | AA23: Restricted | AB23: FALSE | AC23: ABC CDA MC Data Science
B24: ABC PSS Product Data Engineering | C24: Production | E24: PBM (Segment) | F24: 2273613 | G24: Joshua Fredell | H24: Ramchandra Reddy Rupireddy | I24: Ramchandra Reddy Rupireddy | J24: PBM-ABC-Data Engineering-L2 Support | K24: Low Risk | N24: Pharmacy benefits management data engineering application to maintain various semantic data layers required for analytics, operations, and reporting. The application also includes certain medical data such as Prior Authorization. | Q24: Homegrown | S24: IaaS | AA24: Confidential | AB24: FALSE | AC24: ABC PSS Product Data Engineering
B25: ABERateComparisonAPI | C25: Production | E25: HCB | F25: 2646189 | G25: William Bryant | H25: Cecily Santolini | I25: Arockiaswamy Arulraj | K25: Low Risk | N25: REST API to get response back from ABE system for the plan recommendation based on the request submitted from SMART | Q25: Homegrown | S25: PaaS | AA25: Unclassified | AB25: FALSE | AC25: ABERateComparisonAPI
B26: ABHKY_Informatics_Process_Control | C26: Production | E26: HCB | F26: 9857522 | G26: Erin Hall | H26: Erin Hall | I26: Blake Wagner | N26: SQL Server Integration Services (SSIS .dtsx) package utilized by Aetna Better Health of Kentucky Informatics developers to automate data loads and reports | Q26: Homegrown | S26: On Premise | AB26: FALSE | AC26: ABHKY_Informatics_Process_Control
B27: ACA EDGE Data Submission | C27: Production | E27: HCB | F27: system | G27: Errin Crowell | H27: Amee Parikh | I27: Claudia Sophie Israel | K27: Medium Risk | N27: The Application submits IFP and SG Member and Claims data to the EDGE servers for ACA Risk Adjustment. | Q27: Homegrown | S27: On Premise | AA27: Restricted | AB27: FALSE | AC27: ACA EDGE Data Submission
A28: 2039 | B28: ACAS - Automatic Letter Generator | C28: Production | E28: HCB | F28: system | G28: Margaret Barnes | H28: Chris Pierce | I28: Michael Sankner | J28: L1.0-DESKTOP APP SUPPORT | K28: Low Risk | N28: VB application that creates and maintains letters that are sent to Providers and Members. Information is Approved within this application the information will be accessible by ACAS claim processors on the mainframe. This application internally maintains versions of each letter template. | Q28: Homegrown | S28: On Premise | Y28: OI-EF57B37AB0CD4E50A44DF6493FE2291C | AA28: Unclassified | AB28: FALSE | AC28: ACAS - Automatic Letter Generator
A29: 2043 | B29: ACAS - CDL LCI | C29: Production | E29: HCB | F29: system | G29: Elizabeth Chittenden | H29: Ross Labranche | I29: Michael Sankner | J29: L1.0-DESKTOP APP SUPPORT | K29: Low Risk | N29: Desktop application used to maintain : State Rules for Claim Delay Letter Generation, State Rules for Late Claim Interest Calculation and State Conditions for Late Claim Interest Calculation. | Q29: Homegrown | S29: On Premise | Y29: OI-82350A55D4F448599148AC08715871DE | AA29: Unclassified | AB29: FALSE | AC29: ACAS - CDL LCI
A30: 1904 | B30: ACAS Conversion Control Tool | C30: Production | E30: HCB | F30: system | G30: Dorene Ciarcia | H30: Annette Cochran | I30: Michael Sankner | J30: L1.0-DESKTOP APP SUPPORT | K30: Low Risk | N30: Allows business to enter Control Number, Office Key combinations which are used to hold and release claims for new business testing and financial fixes | Q30: Homegrown | S30: On Premise | Y30: OI-2986F5D585E94423A3AAE6BC2C3B1F73 | AA30: Unclassified | AB30: FALSE | AC30: ACAS Conversion Control Tool
A31: 1609 | B31: ACAS Draft Accounting Assignment Tool | C31: Production | E31: HCB | F31: system | G31: Frank Echanique | H31: Jeffry Agnew | I31: Michael Sankner | J31: L1.0-DESKTOP APP SUPPORT | K31: Low Risk | N31: Allows the business to update/maintain the ACAS Bank Account table. | Q31: Homegrown | S31: On Premise | Y31: OI-41825E27C3DA4F5C94BC880BD865121F | AA31: Unclassified | AB31: FALSE | AC31: ACAS Draft Accounting Assignment Tool
B32: ACAS History Reconstruction Tool | C32: Production | E32: HCB | F32: system | G32: Holly Allen | H32: Holly Allen | I32: Adam Kelley | K32: Low Risk | N32: The ACAS History Reconstruction Tool gathers financial and diagnostic information for an individual from the ACAS claim history screens and allows the user to export the data into an Excel spreadsheet. This is useful for file audits, diagnostic trending, and discovering where financial errors may have occurred on a member file. | Q32: Homegrown | S32: On Premise | AA32: Confidential | AB32: FALSE | AC32: ACAS History Reconstruction Tool
B33: ACAS PL EX LookUp | C33: Production | E33: HCB | F33: system | G33: Holly Allen | H33: Holly Allen | I33: Adam Kelley | K33: Low Risk | N33: Application scrapes data from the PL screen in ACAS and then uses that data to scrape from the LA, LI, and/or LK screens to display all scraped in one output. | Q33: Homegrown | S33: On Premise | AA33: Confidential | AB33: FALSE | AC33: ACAS PL EX LookUp
B34: ACC COLLEAGUE TRACK DASHBOARD | C34: Production | E34: Health Care Delivery (HCD) | F34: 2585725 | G34: Kirk Widner | H34: Kirk Widner | I34: Shashwati Ganguly | K34: Low Risk | N34: ACCCOLLEAGUETRACKDB ACC COLLEAGUE TRACK DASHBOARD | Q34: Hybrid | S34: Hybrid | AA34: Confidential | AB34: FALSE | AC34: ACC COLLEAGUE TRACK DASHBOARD
B35: ACCAT (Aetna Claim/Call Analytics Tool) | C35: Production | E35: HCB | F35: system | G35: Elizabeth Linthicum | H35: Kiran Nair | I35: Harisha Reddiboina | J35: Aetna Data Lake Operational Data Store_ADL-ODS | K35: Medium Risk | N35: Calculate first call and first claim resolution based on documentation in ASD/GPS (call) and ACAS (claim) | Q35: Homegrown | S35: IaaS | AA35: Restricted | AB35: FALSE | AC35: ACCAT (Aetna Claim/Call Analytics Tool)
A36: 2463 | B36: Accelerate | C36: Production | E36: ISTS | F36: system | G36: Jay Zirblis | H36: Jay Zirblis | I36: Jay Zirblis | K36: Low Risk | N36: This is a SQL database containing all applications installed on clients at Aetna. 9 data sources currently feed the database including the application inventory. The primary purpose of this system is to play and automate desktop lease replacements and upgrades. | Q36: Homegrown | S36: On Premise | Y36: OI-6F65CBF6B8594E28BA49C83BE50F0B93 | AA36: Confidential | AB36: FALSE | AC36: Accelerate
B37: Access Hub | C37: Production | E37: HCB | F37: system | G37: Lorraine Lord | H37: Claire Jost | I37: Komal Satpathy | J37: Aetna Employer Portal_Assignment_group | N37: A new portal to register and provision users for Plan Sponsor applications with latest tech for better user experience. It replaces existing PSREG application. | Q37: Homegrown | S37: PaaS | AB37: FALSE | AC37: Access Hub
B38: accesscontrolservice | C38: Production | E38: HCB | F38: system | G38: Jinex Thomas Thandiakkal | H38: Jinex Thomas Thandiakkal | I38: Neeta Myageri | J38: L1.0-Framework Services Support | K38: Low Risk | N38: Accesscontrol service is used to update/retrieve the user staus. | Q38: Homegrown | S38: Hybrid | AA38: Unclassified | AB38: FALSE | AC38: accesscontrolservice
A39: 4404 | B39: AccessNow | C39: Production | E39: Corporate | F39: system | G39: Subhashini Natarajan | H39: Subhashini Natarajan | I39: Subhashini Natarajan | K39: High Risk | N39: AccessNow supports the following security business function from, to and for cloud environments: Access Request Access Approval and workflow management Access provisioning Account registration/setup Access Deprovisioning | Q39: COTS | S39: SaaS | Y39: OI-29DA7C4BFB844651AD8510B966424738 | AA39: Restricted | AB39: FALSE | AC39: AccessNow
B40: AccessNow-CVS | C40: Production | E40: Corporate | F40: system | G40: Subhashini Natarajan | H40: Victoria Oravits | I40: Subhashini Natarajan | J40: Self-service Access Request - AccessNow | K40: High Risk | N40: Cloud-based SaaS application supporting the Identity and Access Management (IAM) Provisioning Consolidation. Replaces the Oracle Identity Manager (OIM) system. | Q40: COTS | S40: Hybrid | AA40: Restricted | AB40: FALSE | AC40: AccessNow-CVS
B41: AccessRights | C41: Production | E41: ISTS | F41: 9857522 | G41: James Beyers | H41: Arshad Shaik Ameer | I41: Arshad Shaik Ameer | J41: DevEx Enablement_Console | N41: We are building an agentic ai project for streamlining new hire process. This requires data mining and intelligent recommendation of software and access to determine new hire needs. This agent will also enable new developers ask questions on the systems, understand repos, architecture, help to identify issues with CI CD etc. | Q41: Homegrown | S41: IaaS | AB41: FALSE | AC41: AccessRights
B42: Accordant | C42: Production | E42: PBM (Segment) | F42: 2646189 | G42: Ryan Rowley | H42: Michael Chen | I42: Jimmy Stringer | K42: Low Risk | N42: Accordant provides services to client members to improve health outcomes by managing rare diseases. The services include identifying members with rare diseases, and driving interactions with clinical team to assess and manage member health. This product is a revenue generator for Care Solutions. | Q42: Homegrown | S42: IaaS | AA42: Unclassified | AB42: FALSE | AC42: Accordant
B43: ACCORDANT (ACCORDANT.COM) | C43: Production | E43: Accordant | F43: 2585725 | G43: Matthew Woodward | H43: Kirk Widner | I43: David Bennett | J43: ACCORDANT-DATA WAREHOUSE | K43: High Risk | N43: Accordant provides comprehensive care management services for rare diseases on behalf of our contracted clients, which include health plans, employers, and third party administrators (TPAs). Accordant clients use referral.accordant.com to submit new members into AccordantCare program. | Q43: Homegrown | S43: On Premise | AA43: Restricted | AB43: FALSE | AC43: ACCORDANT (ACCORDANT.COM)
B44: ACCORDANT C&P EXTRACT SERVICES | C44: Production | E44: Health Care Delivery (HCD) | F44: 2585725 | G44: Kirk Widner | H44: Kirk Widner | I44: Shashwati Ganguly | K44: Low Risk | N44: ACCORDANTCPEXTRACTSERV ACCORDANT C&P EXTRACT SERVICES | Q44: Homegrown | S44: Hybrid | AA44: Confidential | AB44: FALSE | AC44: ACCORDANT C&P EXTRACT SERVICES
B45: ACCORDANT CLIENT DATA LOAD SERVICES | C45: Production | E45: Health Care Delivery (HCD) | F45: 2585725 | G45: Kirk Widner | H45: Kirk Widner | I45: Shashwati Ganguly | K45: Low Risk | N45: ACCORDANTCLIENTDATALOAD ACCORDANT CLIENT DATA LOAD SERVICES | Q45: Homegrown | S45: Hybrid | AA45: Confidential | AB45: FALSE | AC45: ACCORDANT CLIENT DATA LOAD SERVICES
B46: ACCORDANT DASHBOARD | C46: Production | E46: Health Care Delivery (HCD) | F46: 2585725 | G46: Kirk Widner | H46: Kirk Widner | I46: Shashwati Ganguly | K46: Low Risk | N46: ACCORDANTDASHBOARD ACCORDANT DASHBOARD | Q46: Homegrown | S46: Hybrid | AA46: Confidential | AB46: FALSE | AC46: ACCORDANT DASHBOARD
B47: ACCORDANT EPIC CABOODLE | C47: Production | E47: Accordant | F47: 2585725 | G47: Kirk Widner | H47: Jayesh Shukla | I47: Michael Talman | J47: CORP-IT-Epic-Technical Systems-L2 Support | K47: Medium Risk | N47: Data warehouse ETL product that allows business users to merge non-Epic data with Epic data. The Accordant Epic Caboodle application is an application that is provided by the Epic vendor to support the Extract-Transform-Load (ETL) functionality of pulling data from the Epic Clarity database daily to the Epic CDW database. This application is used internally by the client support team and is not made available to business users. | Q47: COTS | S47: On Premise | AA47: Restricted | AB47: FALSE | AC47: ACCORDANT EPIC CABOODLE
B48: ACCORDANT EPIC CACHE | C48: Production | E48: Accordant | F48: 2585725 | G48: Kirk Widner | H48: Jayesh Shukla | I48: Michael Talman | J48: CORP-IT-Epic-Technical Systems-L2 Support | K48: Medium Risk | N48: Database servers hosting Epics Electronic Health records in support of Accordant provider workflows | Q48: COTS | S48: On Premise | AA48: Confidential | AB48: FALSE | AC48: ACCORDANT EPIC CACHE
B49: ACCORDANT EPIC CARE EVERYWHERE | C49: Production | E49: Accordant | F49: 2585725 | G49: Kirk Widner | H49: Jayesh Shukla | I49: Michael Talman | J49: CORP-IT-Epic-Technical Systems-L2 Support | K49: Medium Risk | N49: Patient information requests from other affiliates to patients in Accordant and vice versa | Q49: COTS | S49: Hybrid | AA49: Confidential | AB49: FALSE | AC49: ACCORDANT EPIC CARE EVERYWHERE
B50: ACCORDANT EPIC CLARITY | C50: Production | E50: Accordant | F50: 2585725 | G50: Kirk Widner | H50: Jayesh Shukla | I50: Michael Talman | J50: CORP-IT-Epic-Technical Systems-L2 Support | K50: Medium Risk | N50: ETL product that manages/stores Epic data in a SQL Server database for reporting purposes. (Note modification in DR Tier from 3 to 2) The Clinical Services Epic Clarity application is an application that is provided by the Epic vendor to support the Extract-Transform-Load (ETL) functionality of pulling data from the Epic Cache/Chronicles environment to the Clarity database daily. This application is used internally by the client support team and is not made available to business users. | Q50: COTS | S50: On Premise | AA50: Restricted | AB50: FALSE | AC50: ACCORDANT EPIC CLARITY
B51: ACCORDANT EPIC FHIR | C51: Production | E51: Accordant | F51: 2585725 | G51: Kirk Widner | H51: Jayesh Shukla | I51: Michael Talman | J51: CORP-IT-Epic-Technical Systems-L2 Support | K51: High Risk | N51: API to support Promoting Interoperability (Meaningful Use) Objective standards | Q51: COTS | S51: On Premise | AA51: Restricted | AB51: FALSE | AC51: ACCORDANT EPIC FHIR
B52: ACCORDANT EPIC HYPERSPACE WEB | C52: Production | E52: Accordant | F52: 2585725 | G52: Kirk Widner | H52: Jayesh Shukla | I52: Michael Talman | J52: CORP-IT-Epic-Technical Systems-L2 Support | K52: Medium Risk | N52: This application is used by Accordant Nurses to access Epic EHR system where they enter patient information, vitals, symptoms and their prescriptions. Hyperspace workflows that are hosted on web servers instead of the Hyperspace client | Q52: COTS | S52: On Premise | AA52: Confidential | AB52: FALSE | AC52: ACCORDANT EPIC HYPERSPACE WEB
B53: ACCORDANT EPIC KUIPER | C53: Production | E53: Accordant | F53: 2585725 | G53: Kirk Widner | H53: Jayesh Shukla | I53: Michael Talman | J53: CORP-IT-Epic-Technical Systems-L2 Support | K53: Low Risk | N53: Used to deploy/upgrade Epic applications (ie, Interconnect, webblob, Print server, Hyperspsace Web, etc) | Q53: COTS | S53: On Premise | AA53: Unclassified | AB53: FALSE | AC53: ACCORDANT EPIC KUIPER
B54: ACCORDANT EPIC MIRTH | C54: Production | D54: Tier1 | E54: Health Care Delivery (HCD) | F54: 2183761 | G54: Kirk Widner | H54: Kirk Widner | I54: Shashwati Ganguly | J54: CORP-IT-Epic-MinuteClinic DEV-L2 Support | K54: Low Risk | N54: Mirth is an interface engine which routes incoming and outgoing Electronic Health records. | Q54: COTS | S54: On Premise | AA54: Confidential | AB54: FALSE | AC54: ACCORDANT EPIC MIRTH
B55: ACCORDANT EPIC MYCHART | C55: Production | E55: Accordant | F55: 2585725 | G55: Kirk Widner | H55: Jayesh Shukla | I55: Michael Talman | J55: CORP-IT-Epic-Technical Systems-L2 Support | K55: High Risk | N55: Publicly accessible website for patients to access their medical charts | Q55: COTS | S55: On Premise | AA55: Restricted | AB55: FALSE | AC55: ACCORDANT EPIC MYCHART
B56: ACCORDANT EPIC PATIENT ARCHIVE | C56: Production | E56: Accordant | F56: 2585725 | G56: Kirk Widner | H56: Jayesh Shukla | I56: Michael Talman | J56: CORP-IT-Epic-Technical Systems-L2 Support | K56: Medium Risk | N56: Used to Archive Cache data off of Cache database to network storage | Q56: COTS | S56: On Premise | AA56: Confidential | AB56: FALSE | AC56: ACCORDANT EPIC PATIENT ARCHIVE
B57: ACCORDANT EPIC PRINT | C57: Production | E57: Accordant | F57: 2585725 | G57: Kirk Widner | H57: Jayesh Shukla | I57: Michael Talman | J57: CORP-IT-Epic-Technical Systems-L2 Support | K57: Low Risk | N57: Print servers to render server print jobs from Epic | Q57: COTS | S57: On Premise | AA57: Confidential | AB57: FALSE | AC57: ACCORDANT EPIC PRINT
B58: ACCORDANT EPIC SLICER DICER | C58: Production | E58: Accordant | F58: 2585725 | G58: Kirk Widner | H58: Jayesh Shukla | I58: Michael Talman | J58: CORP-IT-Epic-Technical Systems-L2 Support | K58: Low Risk | N58: Reporting tool that reads data from the Caboodle database and allows business users to perform adhoc reporting. The Accordant Epic SlicerDicer application is an application that is provided by the Epic vendor that references the Epic CDW database to present data to the business users via a link the Hyperspace application to perform what-if scenarios on the data. | Q58: COTS | S58: On Premise | AA58: Confidential | AB58: FALSE | AC58: ACCORDANT EPIC SLICER DICER
B59: ACCORDANT EPIC SureScripts Interface | C59: Production | E59: Accordant | F59: 2585725 | G59: Kirk Widner | H59: Jayesh Shukla | I59: Michael Talman | J59: CORP-IT-Epic-Technical Systems-L2 Support | K59: Low Risk | N59: Webservice servers to facilitate communication between surescripts and Epic | Q59: COTS | S59: On Premise | AA59: Confidential | AB59: FALSE | AC59: ACCORDANT EPIC SureScripts Interface
B60: ACCORDANT EXTRANET | C60: Production | E60: Accordant | F60: 2585725 | G60: Matthew Woodward | H60: Kirk Widner | I60: David Bennett | J60: ACCORDANT-DATA WAREHOUSE | K60: High Risk | N60: Accordant provides comprehensive care management services for rare diseases on behalf of our contracted clients, which include health plans, employers, and third party administrators (TPAs). Clients use extranet.accordant.com to access reports and AccordantCare member communications prepared by Accordant analytics team and Program Communication teams. Physicians (member advisory board) use extranet to review Clinical Practice Guidelines developed by Accordant Clinical Operations team. | Q60: Homegrown | S60: On Premise | AA60: Restricted | AB60: FALSE | AC60: ACCORDANT EXTRANET
B61: ACCORDANT INTRANET | C61: Production | E61: Accordant | F61: 2585725 | G61: Matthew Woodward | H61: Kirk Widner | I61: David Bennett | J61: ACCORDANT-DATA WAREHOUSE | K61: Medium Risk | N61: Web/App and printer server. Multiple web applications for raising tickets and requesting changes to Accordant business processes/ACMS/Accordant.com/Extranet. Applications and printers are used by Accordant staff. | Q61: Homegrown | S61: On Premise | AA61: Restricted | AB61: FALSE | AC61: ACCORDANT INTRANET
B62: ACCORDANT RARE - ACMS CVS | C62: Production | E62: Accordant | F62: 2585725 | G62: Matthew Woodward | H62: Kirk Widner | I62: David Bennett | J62: ACCORDANT-DATA WAREHOUSE | K62: High Risk | N62: Accordant provides comprehensive care management services for rare diseases on behalf of our contracted clients, which include health plans, employers, and third party administrators (TPAs). Internal resources utilize ACMS to access the AccordantCare informaiton for members as well as program materials and reports on members participating in the program. | Q62: Hybrid | S62: On Premise | AA62: Restricted | AB62: FALSE | AC62: ACCORDANT RARE - ACMS CVS
B63: ACCORDANT REPORTS MANAGEMENT SYSTEM | C63: Production | E63: Accordant | F63: 2585725 | G63: Matthew Woodward | H63: Kirk Widner | I63: David Bennett | J63: ACCORDANT-DATA WAREHOUSE | K63: Low Risk | N63: Data center for Accordant operations. Servers for the intake of monthly client files for processing patient identification (PID) process to identify potential members that are eligible for the Accordant program | Q63: Homegrown | S63: On Premise | AA63: Confidential | AB63: FALSE | AC63: ACCORDANT REPORTS MANAGEMENT SYSTEM
B64: Account Management - GCP | C64: Production | E64: HCB | F64: 2183761 | G64: Heather Shroyer | H64: Heather Shroyer | I64: Heather Shroyer | K64: Low Risk | N64: Quarterly reports for Plan Sponsor Information from Commercial Account Management Business. This information is for internal HCB Pharmacy with no PHI or PHII. These are not business applications but this is subjected to review. | Q64: Homegrown | S64: Hybrid | AA64: Unclassified | AB64: FALSE | AC64: Account Management - GCP
B65: Account Manager | C65: Production | E65: HCB | F65: system | G65: Ellen Chamberlain | H65: Krishna Pyneni | I65: Shrivallabha Deshpande | J65: Access_Identity_Management_Prod_Support | K65: High Risk | N65: Enterprise suite of Applications for managing identities, providing authentication, authorization, registration & security services to external constituent types like members, brokers, providers etc. | Q65: Homegrown | S65: Hybrid | AA65: Restricted | AB65: FALSE | AC65: Account Manager
B66: Account Manager Communication Preferences | C66: Production | E66: HCB | F66: system | G66: Jessica Manning | H66: Ram Narayan | I66: Cheryl Wahlin | K66: Low Risk | N66: IIB Wrapper service created for Account manager to retrieve preferences | Q66: Homegrown | S66: On Premise | AA66: Confidential | AB66: FALSE | AC66: Account Manager Communication Preferences
B67: Account Revision Tool | C67: Production | E67: HCB | F67: system | G67: Elizabeth Didomizio | H67: America Aa Metz | I67: Mukundan Krishnan | J67: NAPSS - ODI SNOW | K67: Low Risk | N67: Prepare New Business Submission | Q67: Hybrid | S67: On Premise | AA67: Proprietary | AB67: FALSE | AC67: Account Revision Tool
B68: Account Structure Tool | C68: Production | E68: HCB | F68: system | G68: Susan Marimon | H68: America Aa Metz | I68: Mukundan Krishnan | J68: NAPSS - ODI SNOW | K68: Low Risk | N68: Tool to assist in the creation and coding of account structures for plan sponsors | Q68: Homegrown | S68: On Premise | AA68: Confidential | AB68: FALSE | AC68: Account Structure Tool
B69: AccountforLife | C69: Production | E69: Health Care Benefits | F69: system | G69: Ellen Chamberlain | H69: Krishna Pyneni | I69: Shrivallabha Deshpande | K69: Medium Risk | N69: Provides an ability to provision a single account to access every product and service that a person is entitled to regardless of line of business | Q69: Homegrown | S69: On Premise | AA69: Restricted | AB69: FALSE | AC69: AccountforLife
B70: ACCOUNTING AND DISCLOSURE SYSTEM | C70: Production | E70: Retail | F70: system | G70: Marrin Cahn | H70: Anna Shimanek | I70: Jennifer Lyons | J70: PS ADS-RXIMAGING | K70: Low Risk | N70: The purpose of Accounting & Disclosure System (ADS) application is to provide a system for recording requests for patient and prescription information in accordance with HIPAA regulations; and to provide the extracting or reporting of the requested patient and script information. This system is used to extract, view, print and the option to send to the mail facility all information necessary to fulfill customer and federal agency requests. | Q70: Homegrown | S70: PaaS | AA70: Confidential | AB70: FALSE | AC70: ACCOUNTING AND DISCLOSURE SYSTEM
B71: AccountManagerAppConfig_common | C71: Production | E71: HCB | F71: system | G71: Ellen Chamberlain | H71: Krishna Pyneni | I71: Shrivallabha Deshpande | K71: Low Risk | N71: This is UI (front end) component for Account ManagerV3 application (AMV3) which is an enterprise application for identity and access management | Q71: Homegrown | S71: On Premise | AA71: Unclassified | AB71: FALSE | AC71: AccountManagerAppConfig_common
B72: AccountManagerAppConfig_config | C72: Production | E72: HCB | F72: system | G72: Ellen Chamberlain | H72: Krishna Pyneni | I72: Inderpal Bhamra | K72: Low Risk | N72: This is UI (front end) component for Account ManagerV3 application (AMV3) which is an enterprise application for identity and access management | Q72: Homegrown | S72: On Premise | AA72: Unclassified | AB72: FALSE | AC72: AccountManagerAppConfig_config
B73: accountmanagerui | C73: Production | E73: Health Care Benefits | F73: 2638821 | G73: Ellen Chamberlain | H73: Krishna Pyneni | I73: Shrivallabha Deshpande | K73: High Risk | N73: The AccountManager application front end view is being converted to a new ReactJS application as accountmanagerui and will be integrated with backend Java application | Q73: Homegrown | S73: On Premise | AA73: Restricted | AB73: FALSE | AC73: accountmanagerui
A74: 4195 | B74: AccountManagerV3 | C74: Production | E74: HCB | F74: 2638821 | G74: Ellen Chamberlain | H74: Krishna Pyneni | I74: Shrivallabha Deshpande | J74: Access_Identity_Management_Prod_Support | K74: High Risk | N74: Enterprise Application for Logging and Registering into Aetna | Q74: Homegrown | S74: On Premise | Y74: OI-B7208062C1334E9FBD7207D40BC2FECF | AA74: Restricted | AB74: FALSE | AC74: AccountManagerV3
B75: ACCOUNTS PAYABLE (MAINFRAME AP) | C75: Production | E75: Retail | F75: system | G75: Melanie Perkins | H75: John Simpson | I75: Thomas Hurley | K75: Low Risk | N75: Description: Processes Purchase Order, Receipt, and Invoice data. Includes batch feeds to SAP for further processing. Business Function: Process and review financial transactions between the company and its suppliers. | Q75: Homegrown | S75: On Premise | AA75: Confidential | AB75: FALSE | AC75: ACCOUNTS PAYABLE (MAINFRAME AP)
B76: Accum Domain Services | C76: Production | E76: PBM (Segment) | F76: 2638821 | G76: Juan Kamulo Bondad | H76: Juan Kamulo Bondad | I76: Satveer Singh | K76: Low Risk | N76: Accum Domain Services is part PBM Accumulation Domain and it will provide member accumulation benefit details. As part of M3P project new API will be implemented to provide real time member Troop Balance | Q76: Homegrown | S76: PaaS | AA76: Confidential | AB76: FALSE | AC76: Accum Domain Services
A77: 3021 | B77: Accumulator Administration | C77: Production | E77: HCB - Affiliate | F77: 9481581 | G77: Damion Ortega | H77: Mandy Burkholder | I77: Raghavanantham Venkatesan | K77: Low Risk | N77: Internal web application used to administer the Accumulator application for Student Health. | Q77: Homegrown | S77: Hybrid | Y77: OI-E3060B733CBA4D1098A319148C28C699 | AA77: Confidential | AB77: FALSE | AC77: Accumulator Administration
B78: Accumulator Update Tool | C78: Production | E78: HCB | F78: system | G78: Holly Allen | H78: Holly Allen | I78: Adam Kelley | K78: Low Risk | N78: This tool will take in an Excel file and use specific information provided to retrieve member data. That member data will be used to update the patient and family accumulator screens in ACAS. The results of the updates will be exported to a business owned share drive. | Q78: Homegrown | S78: On Premise | AA78: Restricted | AB78: FALSE | AC78: Accumulator Update Tool
B79: Accuracy Improvement and Monitoring | C79: Production | E79: PSS Pharmacy Service Segment | F79: system | G79: Christopher McKenna | H79: Stephen Pattavina | I79: Gurjot Kaur | J79: PBM_EoS_AIM_group | N79: AIM is a component of CFIT program which is part of connected ecosystem. This will produce UWer controlled actuals for EoS client which can be compared with EoS forecast. Produce UWer to FAF disconnects across various parameters and develop detailed forecast vs actual analysis packages to support RC and mitigation strategies. These outputs will be consumed within CFIT, render BI views and will be provided to business users. | Q79: Homegrown | S79: DaaS | AB79: FALSE | AC79: Accuracy Improvement and Monitoring
B80: ACERT | C80: Production | E80: Retail | F80: 9481581 | G80: Jaclyn Stricklin | H80: Jaclyn Stricklin | I80: Richard Gerrits | J80: OMNI-LTC-ANCILLARY | K80: Medium Risk | N80: Two Point provides a software tool called ACERT that allows access to pharmacy data and documents for LTC pharmacy archives. It also provides the ability to generate a report of the same pharmacy information. The CVS LTC Pharmacy data archives and the Two Point ACERT tool (to access this data) will now be hosted internally at the CVS data center. | Q80: COTS | S80: IaaS | AA80: Restricted | AB80: FALSE | AC80: ACERT
B81: ACERT Specialty Archive | C81: Production | E81: Retail | F81: 9485312 | G81: Linda Rivera | H81: Linda Rivera | I81: James McGuire | K81: Low Risk | N81: ACERT is an archive/lookup application from vendor Two Point that stores legacy pharmacy system data from acquisitions that are converted to CVS systems (generally file buys). It is used primarily by pharmacists to pull additional rx info that may not have been migrated to the CVS system, as well as by designated users to fulfill audit requests. | Q81: COTS | S81: IaaS | AA81: Confidential | AB81: FALSE | AC81: ACERT Specialty Archive
B82: Aceyus | C82: Production | E82: HCB | F82: system | G82: Leslie Helton | H82: Mark Bastian | I82: Andreas Ashbery | J82: Corp-IT-ContactCenter-Engineering | K82: Low Risk | N82: Contact center reporting and analytics dashboards designed to help businesses become more efficient and effective across all channels of communication with customers. | Q82: COTS | S82: On Premise | AA82: Confidential | AB82: FALSE | AC82: Aceyus
B83: ACHIEVERS | C83: Production | E83: Corporate | F83: 2585725 | G83: Katrina Ventola | H83: Katrina Ventola | I83: Christopher Cai | K83: Medium Risk | N83: Achievers is the SaaS vendor for our employee recognition program Values in Action. | Q83: COTS | S83: SaaS | AA83: Confidential | AB83: FALSE | AC83: ACHIEVERS
B84: ACHS Access Audit Database / Intake Services Team | C84: Production | E84: HCB | F84: system | G84: William Spring | H84: Daniel Kehl | I84: Leyla Hashim | K84: Low Risk | N84: ACHS Access Audit Database / Intake Services Team web version | Q84: Homegrown | S84: On Premise | AA84: Restricted | AB84: FALSE | AC84: ACHS Access Audit Database / Intake Services Team
B85: ACIS | C85: Production | E85: Coram | F85: 9485312 | G85: Amanda Boyle | H85: Melissa Polich | I85: Melissa Polich | J85: Support_Group_APM0001315 | K85: Medium Risk | N85: ACIS is an Apria developed order intake and shipment system used by the Coram Enteral business. When Coram migrated to CVS this system was transitioned with the business. AS/400 based. | Q85: Homegrown | S85: On Premise | AA85: Restricted | AB85: FALSE | AC85: ACIS
B86: ACQ2.0 | C86: Production | E86: Retail | F86: 9485312 | G86: Jeffrey Ryan | H86: Sophia Beaumariage | I86: Gautam Manchanda | K86: Low Risk | N86: ACQ2.0 is a validation application which loads and validates pharmacy data files (patient, prescriber, Rx) received from an acquired pharmacy prior to loading the data into the main RxConnect Production environment. This application is used by specific internal staff whose responsibilities are to ensure acquisition data is properly tested prior to uploading the data files into the RxConnect Production environment. | Q86: Homegrown | S86: On Premise | AA86: Confidential | AB86: FALSE | AC86: ACQ2.0
A87: 2767 | B87: ACR Summary (Audit Control & Reporting) | C87: Production | E87: HCB | F87: system | G87: Donald Milligan | H87: Donald Milligan | I87: Donald Milligan | J87: L1.0-KB Correspondence EOM Application Support | K87: Low Risk | N87: Batch automated balancing | Q87: COTS | S87: On Premise | Y87: OI-1B43E37607004ECF8D7FDBD643BD7E51 | AA87: Unclassified | AB87: FALSE | AC87: ACR Summary (Audit Control & Reporting)
A88: 907 | B88: ACS Unclaimed Property | C88: Production | E88: Corporate | F88: system | G88: Margaret Pagnillo | H88: Michael Makary | I88: Kannan Srinivasan | J88: L1.0-Corporate Tax and Treasury Application Support | K88: Low Risk | N88: ACS Unclaimed Property application is used to track unclaimed property and their payment statuses. It is used with the ScerIS Imaging application and the data between the two systems is kept in sync. HCB has a site to site VPN connected to Avenu, the ACS Unclaimed Property vendor, which facilitates data transmission between Aetna and Avenu. The DB2 database containing the data, is stored by Avenu (offsite) and the internal component is simply a desktop application with VPN connectivity. | Q88: COTS | S88: On Premise | Y88: OI-B779B967A01B418FBD3C7CCBBE890E5A | AA88: Restricted | AB88: FALSE | AC88: ACS Unclaimed Property
B89: Action Code Search | C89: Production | E89: HCB | F89: system | G89: Holly Allen | H89: Holly Allen | I89: Adam Kelley | K89: Low Risk | N89: Service Members | Q89: Homegrown | S89: On Premise | AA89: Unclassified | AB89: FALSE | AC89: Action Code Search
A90: 4413 | B90: Active Analytics | C90: Production | E90: HCB - Affiliate | F90: system | G90: Khadar Shaik | H90: Saichaitanya Jampana | I90: Saichaitanya Jampana | J90: AHM ActiveHealth Enterprise Reporting Support L2 | K90: Low Risk | N90: The AHM Reporting Portal (called Active Analytics) is an on-line, secure, on-demand reporting portal that supports 24/7 access to two foundation methods of sharing information about a clients population being supported by Active Health: Dashboards that are updated routinely to support the time frames required by the metrics; and Reports (both standard and custom | Q90: Homegrown | S90: On Premise | Y90: OI-6D747DB6503742DE80254D1738E7ED30 | AA90: Unclassified | AB90: FALSE | AC90: Active Analytics
B91: Active Directory | C91: Production | E91: ISTS | F91: 1666280 | G91: Michael Lowe | H91: Elizabeth DeTino-Montgomery | I91: David Harris | J91: DWSD AD Engineering | N91: Active Directory - manages user identities, access, and security policies across enterprise IT systems, enabling centralized authentication and authorization | Q91: Hybrid | S91: Hybrid | AB91: FALSE | AC91: Active Directory
B92: Active Directory Certificate Services & Word Wide Web Publishing Services | C92: Production | E92: HCB | F92: system | G92: Santhosh Srinivasa | H92: David Pelletier | I92: Santhosh Srinivasa | K92: Low Risk | N92: Active Directory Certificate Services Servers: Server Name IP Address mvmpcaint902.aetna.com 157.121.20.151 mvmqcaint902.aetnaq.com 157.121.210.17 wvmpcaint902.aetna.com 157.121.29.31 | Q92: COTS | S92: On Premise | AA92: Unclassified | AB92: FALSE | AC92: Active Directory Certificate Services & Word Wide Web Publishing Services
A93: 2177 | B93: Active Health Interface | C93: Production | E93: HCB | F93: 2183761 | G93: Terry Randolph | H93: Jonah Pasternak | I93: Kevin Buckeridge | J93: Informatics L1 Support Baseline | K93: Low Risk | N93: The Active Health Interface consists of the AHMTool web tool and the batch feeds supporting the delivery of integrated data to Active Health Management (AHM). | Q93: Homegrown | S93: On Premise | Y93: OI-08585AF00AE14D7A80446F8BE8AFD4D8 | AA93: Confidential | AB93: FALSE | AC93: Active Health Interface
B94: Active Health Management Disaster Recovery as a Service | C94: Production | E94: ISTS | F94: 9481581 | G94: Edward Powell | H94: John Wallace | I94: John Moser | N94: Azure Site Replicator to set up disaster recovery copies of virtual machines for Active Health Management. Used for DR testing and DR failover if needed. Needed for tag tagging resources. | Q94: COTS | S94: IaaS | AB94: FALSE | AC94: Active Health Management Disaster Recovery as a Service
B95: ActiveBatch | C95: Production | E95: PBM (Segment) | F95: 9857522 | G95: Tracy Grunsfeld | H95: Tracy Grunsfeld | I95: Jed Knutson | K95: Medium Risk | N95: ActiveBatch schedule software is a vendor softward installed onprem for use for the Novologix platform only. | Q95: COTS | S95: On Premise | AA95: Restricted | AB95: FALSE | AC95: ActiveBatch
B96: ActiveHealth Intelligent Communication Platform | C96: Production | E96: HCB | F96: system | G96: Dea Crose | H96: Priyadharsini Mani | I96: Deepak Vishwanatha Prabhu | J96: AHM ActiveHealth Comm Engine Support L2 | N96: Centralized platform that provides capability to send communications to members via email, sms, push notifications and other channels. | Q96: Homegrown | S96: Hybrid | AB96: FALSE | AC96: ActiveHealth Intelligent Communication Platform
B97: ACTUARIAL DATA REPOSITORY | C97: Production | E97: PBM (Segment) | F97: system | G97: Rebecca Justice | H97: Rebecca Justice | I97: Nicholas Conley | J97: MED D APPDEV COE | K97: Medium Risk | N97: The ADW (Actuarial Data Repository) System maintains data for the business Actuarial staff to utilize when compiling data to support the Trade Relations and Networking departments for their bid process. Much of this data is loaded from the same files and packages used for other PBM - Solon Applications, such as Eligibility, Provider, and others. | Q97: Homegrown | S97: Hybrid | AA97: Restricted | AB97: FALSE | AC97: ACTUARIAL DATA REPOSITORY
B98: Actuarial DataMart | C98: Production | E98: HCB | F98: system | G98: Melissa Askey | H98: Gregory Hassett | I98: John Ivans | K98: Low Risk | N98: ADM is a SQL server based member level data mart used to drive analytics and pricing activities for commercial actuarial. | Q98: Homegrown | S98: On Premise | AA98: Confidential | AB98: FALSE | AC98: Actuarial DataMart
B99: Actuarial Modeling Projections | C99: Production | E99: HCB | F99: system | G99: Melissa Askey | H99: Gregory Hassett | I99: Justin Overturf | K99: Low Risk | N99: AMP is a projection tool which enables actuarial to price all commercial groups in batch style and feed results to the forecasting and block check processes. | Q99: Homegrown | S99: On Premise | AA99: Confidential | AB99: FALSE | AC99: Actuarial Modeling Projections
B100: Actuarial Private Exchange Data Repository | C100: Production | E100: HCB | F100: system | G100: Kory Graber | H100: Ella Morrison | I100: John Ivans | K100: Low Risk | N100: Data Repository to hold Aon Private Exchange data for reporting and analyzing. | Q100: Homegrown | S100: On Premise | AA100: Unclassified | AB100: FALSE | AC100: Actuarial Private Exchange Data Repository
...
